{
  "order": [
    {
      "id": 1,
      "title": "test order",
      "order_detail": "this is order details"
    },
    {
      "FirstName": "Feng",
      "LastName": "Cheng",
      "email": "ycyoungcheng@gmail.com",
      "Birthday": "2020-08-09",
      "Color": "#000000",
      "Bows": "1",
      "id": 2
    },
    {
      "FirstName": "Feng",
      "LastName": "Cheng",
      "email": "ycyoungcheng@gmail.com",
      "Birthday": "2020-08-16",
      "Color": "#6a2525",
      "Bows": "3",
      "id": 3
    },
    {
      "FirstName": "Andrew",
      "LastName": "Cheng",
      "email": "fengcheng0126@gmail.com",
      "Birthday": "2020-08-17",
      "Color": "#484141",
      "Bows": "5",
      "id": 4
    }
  ]
}